slivka/__about__.py
slivka/__init__.py
slivka/__main__.py
slivka/cli.py
slivka/consts.py
slivka/compat/__init__.py
slivka/compat/contextlib.py
slivka/compat/resources.py
slivka/conf/__init__.py
slivka/conf/loaders.py
slivka/conf/logging.py
slivka/conf/partial-settings-schema.json
slivka/conf/service-schema.json
slivka/db/__init__.py
slivka/db/documents.py
slivka/db/helpers.py
slivka/db/mongo_utils.py
slivka/db/repositories.py
slivka/local_queue/__init__.py
slivka/local_queue/client.py
slivka/local_queue/server.py
slivka/migrations/__init__.py
slivka/migrations/__main__.py
slivka/migrations/cli.py
slivka/migrations/migration_1.py
slivka/migrations/migration_2_tz_aware_datetimes.py
slivka/project_template/manage.py
slivka/project_template/routes.py
slivka/project_template/settings.yaml
slivka/project_template/wsgi.py
slivka/project_template/scripts/example.py
slivka/project_template/scripts/selectors.py
slivka/project_template/services/example.service.yaml
slivka/project_template/static/openapi.yaml
slivka/project_template/static/redoc-index.html
slivka/project_template/templates/index.html
slivka/project_template/testdata/example-input.txt
slivka/scheduler/__init__.py
slivka/scheduler/factory.py
slivka/scheduler/scheduler.py
slivka/scheduler/service_monitor.py
slivka/scheduler/runners/__init__.py
slivka/scheduler/runners/_bash_lex.py
slivka/scheduler/runners/grid_engine.py
slivka/scheduler/runners/lsf-runner.bash.tpl
slivka/scheduler/runners/lsf.py
slivka/scheduler/runners/runner.bash.tpl
slivka/scheduler/runners/runner.py
slivka/scheduler/runners/runner.sh.tpl
slivka/scheduler/runners/shell.py
slivka/scheduler/runners/slivka_queue.py
slivka/scheduler/runners/slurm.py
slivka/scheduler/runners/slurm_batch.sh.tpl
slivka/server/__init__.py
slivka/server/api_views.py
slivka/server/media_views.py
slivka/server/forms/__init__.py
slivka/server/forms/fields.py
slivka/server/forms/file_proxy.py
slivka/server/forms/form.py
slivka/server/forms/widgets.py
slivka-0.8.5b7.dist-info/licenses/LICENSE
slivka-0.8.5b7.dist-info/METADATA
slivka-0.8.5b7.dist-info/WHEEL
slivka-0.8.5b7.dist-info/entry_points.txt
slivka-0.8.5b7.dist-info/top_level.txt
slivka-0.8.5b7.dist-info/RECORD
