Metadata-Version: 2.4
Name: slivka
Version: 0.8.5b7
Summary: A toolkit for deploying command-line tools as web services.
Author-email: Mateusz Maciej Warowny <warowny.mateusz@gene.com>, James Procter <j.procter@dundee.ac.uk>
Maintainer-email: Mateusz Maciej Warowny <warowny.mateusz@gene.com>
License-Expression: Apache-2.0
Project-URL: Repository, https://github.com/proteinverse/slivka
Keywords: slivka,scientific-computing,framework,REST-API,command-line-tools,hpc
Classifier: Development Status :: 4 - Beta
Classifier: Framework :: Flask
Classifier: Programming Language :: Python :: 3 :: Only
Classifier: Programming Language :: Python :: 3.7
Classifier: Programming Language :: Python :: 3.8
Classifier: Programming Language :: Python :: 3.9
Classifier: Programming Language :: Python :: 3.10
Classifier: Programming Language :: Python :: 3.11
Classifier: Programming Language :: Python :: 3.12
Classifier: Topic :: Scientific/Engineering :: Bio-Informatics
Classifier: Topic :: System :: Distributed Computing
Requires-Python: >=3.7
License-File: LICENSE
Requires-Dist: attrs>=19.0
Requires-Dist: cachetools>=5.3.3
Requires-Dist: click>=7.0
Requires-Dist: Flask>=2.0
Requires-Dist: frozendict>=1.2
Requires-Dist: jsonschema>=3.0
Requires-Dist: MarkupSafe>=1.0
Requires-Dist: packaging
Requires-Dist: pymongo>=3.7
Requires-Dist: python-daemon>=3.0
Requires-Dist: python-dateutil>=2.8
Requires-Dist: PyYAML>=5.4
Requires-Dist: pyzmq>=19.0
Requires-Dist: ruamel.yaml
Requires-Dist: simplejson>=3.16
Requires-Dist: Werkzeug>=2.0
Provides-Extra: gunicorn
Requires-Dist: gunicorn>=19.9; extra == "gunicorn"
Provides-Extra: uwsgi
Requires-Dist: uWSGI>=2.0; extra == "uwsgi"
Provides-Extra: bioinformatics
Requires-Dist: biopython>=1.72; extra == "bioinformatics"
Provides-Extra: test
Requires-Dist: mongomock>=3.18; extra == "test"
Requires-Dist: PyHamcrest>=2.0.4; extra == "test"
Requires-Dist: pytest-raises>=0.11; extra == "test"
Requires-Dist: pytest>=7.4; extra == "test"
Requires-Dist: sentinels>=1.0.0; extra == "test"
Dynamic: license-file
